SeisLog/SeisLog.py
SeisLog/__init__.py
SeisLog-0.1.2.dist-info/License.md
SeisLog-0.1.2.dist-info/METADATA
SeisLog-0.1.2.dist-info/WHEEL
SeisLog-0.1.2.dist-info/top_level.txt
SeisLog-0.1.2.dist-info/RECORD
