Metadata-Version: 2.1
Name: SeisLog
Version: 0.1.2
Summary: Extracts the seismic trace (on depth data) along some wellbore given its deviation survey.
Home-page: http://pypi.python.org/pypi/SeisLog/
Author: Samara Omar
Author-email: somar@mines.edu
License: LICENSE.md
Platform: UNKNOWN
License-File: License.md
Requires-Dist: dask (==2021.10.0)
Requires-Dist: segysak
Requires-Dist: matplotlib
Requires-Dist: numpy
Requires-Dist: pandas
Requires-Dist: lasio
Requires-Dist: welly
